archivertools/__init__.py
archivertools-0.0.2.dev2.dist-info/DESCRIPTION.rst
archivertools-0.0.2.dev2.dist-info/METADATA
archivertools-0.0.2.dev2.dist-info/RECORD
archivertools-0.0.2.dev2.dist-info/WHEEL
archivertools-0.0.2.dev2.dist-info/metadata.json
archivertools-0.0.2.dev2.dist-info/top_level.txt
