Metadata-Version: 2.0
Name: archivertools
Version: 0.0.2.dev2
Summary: tools for use with Data Togethermorph.io archival scraping work
Home-page: https://github.com/datatogether/archivertools
Author: Jeffrey Liu
Author-email: email.jeffrey.liu@gmail.com
License: GNU AGPL v3
Platform: UNKNOWN
Requires-Dist: requests
Requires-Dist: sqlalchemy
Requires-Dist: urllib3
